retroviz/__init__.py
retroviz-0.6.dist-info/LICENSE
retroviz-0.6.dist-info/METADATA
retroviz-0.6.dist-info/WHEEL
retroviz-0.6.dist-info/top_level.txt
retroviz-0.6.dist-info/RECORD
