Metadata-Version: 2.1
Name: retroviz
Version: 0.6
Summary: RETRO-VIZ
Home-page: https://github.com/kimdebie/retroviz
Author: Kim de Bie
Author-email: kimdebie@outlook.com
License: UNKNOWN
Platform: UNKNOWN
Classifier: Programming Language :: Python :: 3
Classifier: License :: OSI Approved :: MIT License
Classifier: Operating System :: OS Independent
Requires-Python: >=3.6
Requires-Dist: numpy
Requires-Dist: scikit-learn (>=0.21.3)
